youtube_playlist_randomizer/__init__.py
youtube_playlist_randomizer/arg_parser.py
youtube_playlist_randomizer/auth.py
youtube_playlist_randomizer/main.py
youtube_playlist_randomizer/playlist.py
youtube_playlist_randomizer/playlistitem.py
youtube_playlist_randomizer/py.typed
youtube_playlist_randomizer/randomizer.py
youtube_playlist_randomizer-0.5.2.dist-info/LICENSE
youtube_playlist_randomizer-0.5.2.dist-info/METADATA
youtube_playlist_randomizer-0.5.2.dist-info/WHEEL
youtube_playlist_randomizer-0.5.2.dist-info/entry_points.txt
youtube_playlist_randomizer-0.5.2.dist-info/RECORD
