Metadata-Version: 2.3
Name: youtube-playlist-randomizer
Version: 0.5.2
Summary: A tool to randomize youtube playlists
License: MIT
Author: Martyn van Dijke
Author-email: martijnvdijke600@gmail.com
Requires-Python: >=3.10,<4.0
Classifier: License :: OSI Approved :: MIT License
Classifier: Programming Language :: Python :: 3
Classifier: Programming Language :: Python :: 3.10
Classifier: Programming Language :: Python :: 3.11
Classifier: Programming Language :: Python :: 3.12
Classifier: Programming Language :: Python :: 3.13
Requires-Dist: google-api-python-client (==1.7.2)
Requires-Dist: google-auth (==2.14.1)
Requires-Dist: google-auth-httplib2 (==0.0.3)
Requires-Dist: google-auth-oauthlib (==0.4.1)
Requires-Dist: prompt-toolkit (>=3.0.51,<4.0.0)
Requires-Dist: prompt-toolkit2 (>=2.0.11,<3.0.0)
